{
	"name": "Copy_AmysqlDB_to_SysDW_T2",
	"properties": {
		"activities": [
			{
				"name": "ForEach_o15",
				"type": "ForEach",
				"dependsOn": [],
				"userProperties": [],
				"typeProperties": {
					"items": {
						"value": "@pipeline().parameters.cw_items",
						"type": "Expression"
					},
					"activities": [
						{
							"name": "Copy_o15",
							"type": "Copy",
							"dependsOn": [],
							"policy": {
								"timeout": "7.00:00:00",
								"retry": 0,
								"retryIntervalInSeconds": 30,
								"secureOutput": false,
								"secureInput": false
							},
							"userProperties": [
								{
									"name": "Source",
									"value": "@{item().source.tableName}"
								},
								{
									"name": "Destination",
									"value": "slt_test.@{item().destination.table}"
								}
							],
							"typeProperties": {
								"source": {
									"type": "AzureMySqlSource"
								},
								"sink": {
									"type": "AzureSqlSink",
									"preCopyScript": {
										"value": "@concat('Truncate table slt_test.' , item().destination.table)",
										"type": "Expression"
									},
									"tableOption": "autoCreate",
									"disableMetricsCollection": false
								},
								"enableStaging": false,
								"validateDataConsistency": false,
								"translator": {
									"value": "@item().copyActivity.translator",
									"type": "Expression"
								}
							},
							"inputs": [
								{
									"referenceName": "SourceDataset_o15",
									"type": "DatasetReference",
									"parameters": {
										"cw_tableName": "@item().source.tableName"
									}
								}
							],
							"outputs": [
								{
									"referenceName": "DestinationDataset_o15",
									"type": "DatasetReference",
									"parameters": {
										"cw_table": "@item().destination.table"
									}
								}
							]
						}
					]
				}
			}
		],
		"parameters": {
			"cw_items": {
				"type": "Array",
				"defaultValue": [
					{
						"source": {
							"tableName": "auftrag"
						},
						"destination": {
							"table": "auftrag"
						},
						"copyActivity": {
							"translator": {
								"type": "TabularTranslator",
								"mappings": [
									{
										"source": {
											"name": "AuftragID",
											"type": "Int32",
											"physicalType": "int"
										},
										"sink": {
											"name": "AuftragID",
											"type": "Int32",
											"physicalType": "int"
										}
									},
									{
										"source": {
											"name": "AuftragsDatum",
											"type": "DateTime",
											"physicalType": "datetime"
										},
										"sink": {
											"name": "AuftragsDatum",
											"type": "DateTime",
											"physicalType": "datetime2"
										}
									},
									{
										"source": {
											"name": "Status",
											"type": "Int32",
											"physicalType": "int"
										},
										"sink": {
											"name": "Status",
											"type": "Int32",
											"physicalType": "int"
										}
									},
									{
										"source": {
											"name": "IDKunde",
											"type": "Int32",
											"physicalType": "int"
										},
										"sink": {
											"name": "IDKunde",
											"type": "Int32",
											"physicalType": "int"
										}
									},
									{
										"source": {
											"name": "AngebotNr",
											"type": "String",
											"physicalType": "varchar"
										},
										"sink": {
											"name": "AngebotNr",
											"type": "String",
											"physicalType": "varchar"
										}
									},
									{
										"source": {
											"name": "AuftragAusAngebotID",
											"type": "Int32",
											"physicalType": "int"
										},
										"sink": {
											"name": "AuftragAusAngebotID",
											"type": "Int32",
											"physicalType": "int"
										}
									},
									{
										"source": {
											"name": "Version",
											"type": "String",
											"physicalType": "varchar"
										},
										"sink": {
											"name": "Version",
											"type": "String",
											"physicalType": "varchar"
										}
									},
									{
										"source": {
											"name": "Bezeichnung",
											"type": "String",
											"physicalType": "text"
										},
										"sink": {
											"name": "Bezeichnung",
											"type": "String",
											"physicalType": "varchar"
										}
									},
									{
										"source": {
											"name": "Gegenstand",
											"type": "String",
											"physicalType": "longtext"
										},
										"sink": {
											"name": "Gegenstand",
											"type": "String",
											"physicalType": "varchar"
										}
									},
									{
										"source": {
											"name": "DatumAngebot",
											"type": "DateTime",
											"physicalType": "datetime"
										},
										"sink": {
											"name": "DatumAngebot",
											"type": "DateTime",
											"physicalType": "datetime2"
										}
									},
									{
										"source": {
											"name": "DatumAnfrage",
											"type": "DateTime",
											"physicalType": "datetime"
										},
										"sink": {
											"name": "DatumAnfrage",
											"type": "DateTime",
											"physicalType": "datetime2"
										}
									},
									{
										"source": {
											"name": "DatumBindefrist",
											"type": "DateTime",
											"physicalType": "datetime"
										},
										"sink": {
											"name": "DatumBindefrist",
											"type": "DateTime",
											"physicalType": "datetime2"
										}
									},
									{
										"source": {
											"name": "IhrZeichen",
											"type": "String",
											"physicalType": "longtext"
										},
										"sink": {
											"name": "IhrZeichen",
											"type": "String",
											"physicalType": "varchar"
										}
									},
									{
										"source": {
											"name": "Vorbehalt",
											"type": "String",
											"physicalType": "longtext"
										},
										"sink": {
											"name": "Vorbehalt",
											"type": "String",
											"physicalType": "varchar"
										}
									},
									{
										"source": {
											"name": "Preis",
											"type": "Double",
											"physicalType": "double"
										},
										"sink": {
											"name": "Preis",
											"type": "Decimal",
											"physicalType": "numeric"
										}
									},
									{
										"source": {
											"name": "RabattBetrag",
											"type": "Double",
											"physicalType": "double"
										},
										"sink": {
											"name": "RabattBetrag",
											"type": "Decimal",
											"physicalType": "numeric"
										}
									},
									{
										"source": {
											"name": "RabattSatz",
											"type": "Double",
											"physicalType": "double"
										},
										"sink": {
											"name": "RabattSatz",
											"type": "Decimal",
											"physicalType": "numeric"
										}
									},
									{
										"source": {
											"name": "MWStSatz1",
											"type": "Double",
											"physicalType": "double"
										},
										"sink": {
											"name": "MWStSatz1",
											"type": "Decimal",
											"physicalType": "numeric"
										}
									},
									{
										"source": {
											"name": "MWStSatz2",
											"type": "Double",
											"physicalType": "double"
										},
										"sink": {
											"name": "MWStSatz2",
											"type": "Decimal",
											"physicalType": "numeric"
										}
									},
									{
										"source": {
											"name": "MWStBrutto1",
											"type": "Double",
											"physicalType": "double"
										},
										"sink": {
											"name": "MWStBrutto1",
											"type": "Decimal",
											"physicalType": "numeric"
										}
									},
									{
										"source": {
											"name": "MWStBrutto2",
											"type": "Double",
											"physicalType": "double"
										},
										"sink": {
											"name": "MWStBrutto2",
											"type": "Decimal",
											"physicalType": "numeric"
										}
									},
									{
										"source": {
											"name": "SkontoText",
											"type": "String",
											"physicalType": "varchar"
										},
										"sink": {
											"name": "SkontoText",
											"type": "String",
											"physicalType": "varchar"
										}
									},
									{
										"source": {
											"name": "RabattText",
											"type": "String",
											"physicalType": "varchar"
										},
										"sink": {
											"name": "RabattText",
											"type": "String",
											"physicalType": "varchar"
										}
									},
									{
										"source": {
											"name": "IDAnsprechpartner",
											"type": "Int32",
											"physicalType": "int"
										},
										"sink": {
											"name": "IDAnsprechpartner",
											"type": "Int32",
											"physicalType": "int"
										}
									},
									{
										"source": {
											"name": "DatumAnlage",
											"type": "DateTime",
											"physicalType": "datetime"
										},
										"sink": {
											"name": "DatumAnlage",
											"type": "DateTime",
											"physicalType": "datetime2"
										}
									},
									{
										"source": {
											"name": "DatumZIP",
											"type": "DateTime",
											"physicalType": "datetime"
										},
										"sink": {
											"name": "DatumZIP",
											"type": "DateTime",
											"physicalType": "datetime2"
										}
									},
									{
										"source": {
											"name": "Leistung",
											"type": "String",
											"physicalType": "longtext"
										},
										"sink": {
											"name": "Leistung",
											"type": "String",
											"physicalType": "varchar"
										}
									},
									{
										"source": {
											"name": "MemoProjektleitung",
											"type": "String",
											"physicalType": "longtext"
										},
										"sink": {
											"name": "MemoProjektleitung",
											"type": "String",
											"physicalType": "varchar"
										}
									},
									{
										"source": {
											"name": "WithMemoAlert",
											"type": "Int32",
											"physicalType": "int"
										},
										"sink": {
											"name": "WithMemoAlert",
											"type": "Int32",
											"physicalType": "int"
										}
									},
									{
										"source": {
											"name": "IDAuftragArt",
											"type": "Int32",
											"physicalType": "int"
										},
										"sink": {
											"name": "IDAuftragArt",
											"type": "Int32",
											"physicalType": "int"
										}
									},
									{
										"source": {
											"name": "IDWaehrung",
											"type": "Int32",
											"physicalType": "int"
										},
										"sink": {
											"name": "IDWaehrung",
											"type": "Int32",
											"physicalType": "int"
										}
									},
									{
										"source": {
											"name": "KursBeiAnlage",
											"type": "Double",
											"physicalType": "double"
										},
										"sink": {
											"name": "KursBeiAnlage",
											"type": "Double",
											"physicalType": "float"
										}
									},
									{
										"source": {
											"name": "AnschriftID",
											"type": "Int32",
											"physicalType": "int"
										},
										"sink": {
											"name": "AnschriftID",
											"type": "Int32",
											"physicalType": "int"
										}
									},
									{
										"source": {
											"name": "AnzeigeName",
											"type": "String",
											"physicalType": "varchar"
										},
										"sink": {
											"name": "AnzeigeName",
											"type": "String",
											"physicalType": "varchar"
										}
									},
									{
										"source": {
											"name": "LieferDatum",
											"type": "DateTime",
											"physicalType": "datetime"
										},
										"sink": {
											"name": "LieferDatum",
											"type": "DateTime",
											"physicalType": "datetime2"
										}
									},
									{
										"source": {
											"name": "VorkasseGezahlt",
											"type": "Int32",
											"physicalType": "int"
										},
										"sink": {
											"name": "VorkasseGezahlt",
											"type": "Int32",
											"physicalType": "int"
										}
									},
									{
										"source": {
											"name": "AdditionalAnschrift1",
											"type": "Int32",
											"physicalType": "int"
										},
										"sink": {
											"name": "AdditionalAnschrift1",
											"type": "Int32",
											"physicalType": "int"
										}
									},
									{
										"source": {
											"name": "AdditionalAnschrift2",
											"type": "Int32",
											"physicalType": "int"
										},
										"sink": {
											"name": "AdditionalAnschrift2",
											"type": "Int32",
											"physicalType": "int"
										}
									},
									{
										"source": {
											"name": "LieferAnschriftID",
											"type": "Int32",
											"physicalType": "int"
										},
										"sink": {
											"name": "LieferAnschriftID",
											"type": "Int32",
											"physicalType": "int"
										}
									},
									{
										"source": {
											"name": "Anschrift1Ansprechpartner",
											"type": "Int32",
											"physicalType": "int"
										},
										"sink": {
											"name": "Anschrift1Ansprechpartner",
											"type": "Int32",
											"physicalType": "int"
										}
									},
									{
										"source": {
											"name": "Anschrift2Ansprechpartner",
											"type": "Int32",
											"physicalType": "int"
										},
										"sink": {
											"name": "Anschrift2Ansprechpartner",
											"type": "Int32",
											"physicalType": "int"
										}
									},
									{
										"source": {
											"name": "AbholAnschrift1",
											"type": "Int32",
											"physicalType": "int"
										},
										"sink": {
											"name": "AbholAnschrift1",
											"type": "Int32",
											"physicalType": "int"
										}
									},
									{
										"source": {
											"name": "AbholAnschrift2",
											"type": "Int32",
											"physicalType": "int"
										},
										"sink": {
											"name": "AbholAnschrift2",
											"type": "Int32",
											"physicalType": "int"
										}
									},
									{
										"source": {
											"name": "LieferBemerkung",
											"type": "String",
											"physicalType": "longtext"
										},
										"sink": {
											"name": "LieferBemerkung",
											"type": "String",
											"physicalType": "varchar"
										}
									},
									{
										"source": {
											"name": "VorlageID",
											"type": "Int32",
											"physicalType": "int"
										},
										"sink": {
											"name": "VorlageID",
											"type": "Int32",
											"physicalType": "int"
										}
									},
									{
										"source": {
											"name": "AuftragAusAnfrageID",
											"type": "Int32",
											"physicalType": "int"
										},
										"sink": {
											"name": "AuftragAusAnfrageID",
											"type": "Int32",
											"physicalType": "int"
										}
									},
									{
										"source": {
											"name": "UpdateableTextBaseID",
											"type": "Int32",
											"physicalType": "int"
										},
										"sink": {
											"name": "UpdateableTextBaseID",
											"type": "Int32",
											"physicalType": "int"
										}
									},
									{
										"source": {
											"name": "MWStSatz3",
											"type": "Double",
											"physicalType": "double"
										},
										"sink": {
											"name": "MWStSatz3",
											"type": "Double",
											"physicalType": "float"
										}
									},
									{
										"source": {
											"name": "MWStBrutto3",
											"type": "Double",
											"physicalType": "double"
										},
										"sink": {
											"name": "MWStBrutto3",
											"type": "Double",
											"physicalType": "float"
										}
									},
									{
										"source": {
											"name": "TextModulTextID_1",
											"type": "Int32",
											"physicalType": "int"
										},
										"sink": {
											"name": "TextModulTextID_1",
											"type": "Int32",
											"physicalType": "int"
										}
									},
									{
										"source": {
											"name": "TextModulTextID_2",
											"type": "Int32",
											"physicalType": "int"
										},
										"sink": {
											"name": "TextModulTextID_2",
											"type": "Int32",
											"physicalType": "int"
										}
									},
									{
										"source": {
											"name": "TextModulTextID_3",
											"type": "Int32",
											"physicalType": "int"
										},
										"sink": {
											"name": "TextModulTextID_3",
											"type": "Int32",
											"physicalType": "int"
										}
									},
									{
										"source": {
											"name": "TextModulTextID_4",
											"type": "Int32",
											"physicalType": "int"
										},
										"sink": {
											"name": "TextModulTextID_4",
											"type": "Int32",
											"physicalType": "int"
										}
									},
									{
										"source": {
											"name": "TextModulTextID_5",
											"type": "Int32",
											"physicalType": "int"
										},
										"sink": {
											"name": "TextModulTextID_5",
											"type": "Int32",
											"physicalType": "int"
										}
									},
									{
										"source": {
											"name": "AuftragBudget",
											"type": "Double",
											"physicalType": "double"
										},
										"sink": {
											"name": "AuftragBudget",
											"type": "Double",
											"physicalType": "float"
										}
									},
									{
										"source": {
											"name": "ForumThreadID",
											"type": "Int32",
											"physicalType": "int"
										},
										"sink": {
											"name": "ForumThreadID",
											"type": "Int32",
											"physicalType": "int"
										}
									},
									{
										"source": {
											"name": "BearbeitungForum",
											"type": "Int32",
											"physicalType": "int"
										},
										"sink": {
											"name": "BearbeitungForum",
											"type": "Int32",
											"physicalType": "int"
										}
									},
									{
										"source": {
											"name": "StatusArchivierung",
											"type": "Int32",
											"physicalType": "int"
										},
										"sink": {
											"name": "StatusArchivierung",
											"type": "Int32",
											"physicalType": "int"
										}
									},
									{
										"source": {
											"name": "ForumID",
											"type": "Int32",
											"physicalType": "int"
										},
										"sink": {
											"name": "ForumID",
											"type": "Int32",
											"physicalType": "int"
										}
									},
									{
										"source": {
											"name": "Kurzfassung_Anzeigen",
											"type": "Int32",
											"physicalType": "int"
										},
										"sink": {
											"name": "Kurzfassung_Anzeigen",
											"type": "Int32",
											"physicalType": "int"
										}
									},
									{
										"source": {
											"name": "TextModulText_1",
											"type": "String",
											"physicalType": "text"
										},
										"sink": {
											"name": "TextModulText_1",
											"type": "String",
											"physicalType": "varchar"
										}
									},
									{
										"source": {
											"name": "TextModulText_2",
											"type": "String",
											"physicalType": "text"
										},
										"sink": {
											"name": "TextModulText_2",
											"type": "String",
											"physicalType": "varchar"
										}
									},
									{
										"source": {
											"name": "TextModulText_3",
											"type": "String",
											"physicalType": "text"
										},
										"sink": {
											"name": "TextModulText_3",
											"type": "String",
											"physicalType": "varchar"
										}
									},
									{
										"source": {
											"name": "TextModulText_4",
											"type": "String",
											"physicalType": "text"
										},
										"sink": {
											"name": "TextModulText_4",
											"type": "String",
											"physicalType": "varchar"
										}
									},
									{
										"source": {
											"name": "TextModulText_5",
											"type": "String",
											"physicalType": "text"
										},
										"sink": {
											"name": "TextModulText_5",
											"type": "String",
											"physicalType": "varchar"
										}
									},
									{
										"source": {
											"name": "EndKundeID",
											"type": "Int32",
											"physicalType": "int"
										},
										"sink": {
											"name": "EndKundeID",
											"type": "Int32",
											"physicalType": "int"
										}
									},
									{
										"source": {
											"name": "AbschlussdatumAuftrag",
											"type": "DateTime",
											"physicalType": "datetime"
										},
										"sink": {
											"name": "AbschlussdatumAuftrag",
											"type": "DateTime",
											"physicalType": "datetime2"
										}
									},
									{
										"source": {
											"name": "MandantID",
											"type": "Int32",
											"physicalType": "int"
										},
										"sink": {
											"name": "MandantID",
											"type": "Int32",
											"physicalType": "int"
										}
									},
									{
										"source": {
											"name": "IndirekterKundeAnsprechpartnerID",
											"type": "Int32",
											"physicalType": "int"
										},
										"sink": {
											"name": "IndirekterKundeAnsprechpartnerID",
											"type": "Int32",
											"physicalType": "int"
										}
									},
									{
										"source": {
											"name": "MWStSatz4",
											"type": "Double",
											"physicalType": "double"
										},
										"sink": {
											"name": "MWStSatz4",
											"type": "Double",
											"physicalType": "float"
										}
									},
									{
										"source": {
											"name": "MWStBrutto4",
											"type": "Double",
											"physicalType": "double"
										},
										"sink": {
											"name": "MWStBrutto4",
											"type": "Double",
											"physicalType": "float"
										}
									},
									{
										"source": {
											"name": "CAT_Art",
											"type": "Int32",
											"physicalType": "int"
										},
										"sink": {
											"name": "CAT_Art",
											"type": "Int32",
											"physicalType": "int"
										}
									},
									{
										"source": {
											"name": "Zeitzone",
											"type": "String",
											"physicalType": "varchar"
										},
										"sink": {
											"name": "Zeitzone",
											"type": "String",
											"physicalType": "varchar"
										}
									},
									{
										"source": {
											"name": "ProjektMaske",
											"type": "Int32",
											"physicalType": "int"
										},
										"sink": {
											"name": "ProjektMaske",
											"type": "Int32",
											"physicalType": "int"
										}
									},
									{
										"source": {
											"name": "StartDatum_Projekt",
											"type": "DateTime",
											"physicalType": "datetime"
										},
										"sink": {
											"name": "StartDatum_Projekt",
											"type": "DateTime",
											"physicalType": "datetime2"
										}
									},
									{
										"source": {
											"name": "EndDatum_Projekt",
											"type": "DateTime",
											"physicalType": "datetime"
										},
										"sink": {
											"name": "EndDatum_Projekt",
											"type": "DateTime",
											"physicalType": "datetime2"
										}
									},
									{
										"source": {
											"name": "AnschriftID_Projekt",
											"type": "Int32",
											"physicalType": "int"
										},
										"sink": {
											"name": "AnschriftID_Projekt",
											"type": "Int32",
											"physicalType": "int"
										}
									},
									{
										"source": {
											"name": "InklusiveWochenende",
											"type": "Int32",
											"physicalType": "int"
										},
										"sink": {
											"name": "InklusiveWochenende",
											"type": "Int32",
											"physicalType": "int"
										}
									},
									{
										"source": {
											"name": "MandantID_Rechnung",
											"type": "Int32",
											"physicalType": "int"
										},
										"sink": {
											"name": "MandantID_Rechnung",
											"type": "Int32",
											"physicalType": "int"
										}
									},
									{
										"source": {
											"name": "Zielrendite",
											"type": "Double",
											"physicalType": "double"
										},
										"sink": {
											"name": "Zielrendite",
											"type": "Double",
											"physicalType": "float"
										}
									},
									{
										"source": {
											"name": "UserDefinedString",
											"type": "String",
											"physicalType": "text"
										},
										"sink": {
											"name": "UserDefinedString",
											"type": "String",
											"physicalType": "varchar"
										}
									},
									{
										"source": {
											"name": "UserDefined_Long1",
											"type": "Int32",
											"physicalType": "int"
										},
										"sink": {
											"name": "UserDefined_Long1",
											"type": "Int32",
											"physicalType": "int"
										}
									},
									{
										"source": {
											"name": "MWStSatz5",
											"type": "Double",
											"physicalType": "double"
										},
										"sink": {
											"name": "MWStSatz5",
											"type": "Double",
											"physicalType": "float"
										}
									},
									{
										"source": {
											"name": "MWStBrutto5",
											"type": "Double",
											"physicalType": "double"
										},
										"sink": {
											"name": "MWStBrutto5",
											"type": "Double",
											"physicalType": "float"
										}
									},
									{
										"source": {
											"name": "DokumentHerkunft",
											"type": "Int32",
											"physicalType": "int"
										},
										"sink": {
											"name": "DokumentHerkunft",
											"type": "Int32",
											"physicalType": "int"
										}
									},
									{
										"source": {
											"name": "Kostenstelle",
											"type": "String",
											"physicalType": "varchar"
										},
										"sink": {
											"name": "Kostenstelle",
											"type": "String",
											"physicalType": "varchar"
										}
									},
									{
										"source": {
											"name": "UserDefined_String2",
											"type": "String",
											"physicalType": "varchar"
										},
										"sink": {
											"name": "UserDefined_String2",
											"type": "String",
											"physicalType": "varchar"
										}
									},
									{
										"source": {
											"name": "DocVersioning",
											"type": "Int32",
											"physicalType": "int"
										},
										"sink": {
											"name": "DocVersioning",
											"type": "Int32",
											"physicalType": "int"
										}
									},
									{
										"source": {
											"name": "ZusatzEmpfaenger",
											"type": "String",
											"physicalType": "text"
										},
										"sink": {
											"name": "ZusatzEmpfaenger",
											"type": "String",
											"physicalType": "varchar"
										}
									},
									{
										"source": {
											"name": "InklusiveSonntag",
											"type": "Int32",
											"physicalType": "int"
										},
										"sink": {
											"name": "InklusiveSonntag",
											"type": "Int32",
											"physicalType": "int"
										}
									},
									{
										"source": {
											"name": "EN15038Konform_Soll",
											"type": "Int32",
											"physicalType": "int"
										},
										"sink": {
											"name": "EN15038Konform_Soll",
											"type": "Int32",
											"physicalType": "int"
										}
									},
									{
										"source": {
											"name": "EN15038Konform_Ist",
											"type": "Int32",
											"physicalType": "int"
										},
										"sink": {
											"name": "EN15038Konform_Ist",
											"type": "Int32",
											"physicalType": "int"
										}
									},
									{
										"source": {
											"name": "EN15038PositionID_Invalid",
											"type": "Int32",
											"physicalType": "int"
										},
										"sink": {
											"name": "EN15038PositionID_Invalid",
											"type": "Int32",
											"physicalType": "int"
										}
									},
									{
										"source": {
											"name": "KundentypFuerAbrechnung",
											"type": "Int32",
											"physicalType": "int"
										},
										"sink": {
											"name": "KundentypFuerAbrechnung",
											"type": "Int32",
											"physicalType": "int"
										}
									},
									{
										"source": {
											"name": "BudgetArt",
											"type": "Int32",
											"physicalType": "int"
										},
										"sink": {
											"name": "BudgetArt",
											"type": "Int32",
											"physicalType": "int"
										}
									},
									{
										"source": {
											"name": "PLMemo_InJobKopieren",
											"type": "Int32",
											"physicalType": "int"
										},
										"sink": {
											"name": "PLMemo_InJobKopieren",
											"type": "Int32",
											"physicalType": "int"
										}
									},
									{
										"source": {
											"name": "ProjektHierarchie",
											"type": "Int32",
											"physicalType": "int"
										},
										"sink": {
											"name": "ProjektHierarchie",
											"type": "Int32",
											"physicalType": "int"
										}
									},
									{
										"source": {
											"name": "HauptProjektID",
											"type": "Int32",
											"physicalType": "int"
										},
										"sink": {
											"name": "HauptProjektID",
											"type": "Int32",
											"physicalType": "int"
										}
									},
									{
										"source": {
											"name": "AktuelleKundenReklamation",
											"type": "Int32",
											"physicalType": "int"
										},
										"sink": {
											"name": "AktuelleKundenReklamation",
											"type": "Int32",
											"physicalType": "int"
										}
									},
									{
										"source": {
											"name": "EinKundeProHauptAuftrag",
											"type": "Int32",
											"physicalType": "int"
										},
										"sink": {
											"name": "EinKundeProHauptAuftrag",
											"type": "Int32",
											"physicalType": "int"
										}
									},
									{
										"source": {
											"name": "EmailCCAdressen",
											"type": "String",
											"physicalType": "text"
										},
										"sink": {
											"name": "EmailCCAdressen",
											"type": "String",
											"physicalType": "varchar"
										}
									},
									{
										"source": {
											"name": "Auftrag_Intern",
											"type": "Int32",
											"physicalType": "int"
										},
										"sink": {
											"name": "Auftrag_Intern",
											"type": "Int32",
											"physicalType": "int"
										}
									},
									{
										"source": {
											"name": "AuftragAusJobAustausch",
											"type": "Int32",
											"physicalType": "int"
										},
										"sink": {
											"name": "AuftragAusJobAustausch",
											"type": "Int32",
											"physicalType": "int"
										}
									},
									{
										"source": {
											"name": "CATUebernahmeTyp",
											"type": "Int32",
											"physicalType": "int"
										},
										"sink": {
											"name": "CATUebernahmeTyp",
											"type": "Int32",
											"physicalType": "int"
										}
									},
									{
										"source": {
											"name": "PositionID_Sprachunabhaengig",
											"type": "Int32",
											"physicalType": "int"
										},
										"sink": {
											"name": "PositionID_Sprachunabhaengig",
											"type": "Int32",
											"physicalType": "int"
										}
									},
									{
										"source": {
											"name": "IDSuchSchablone",
											"type": "Int32",
											"physicalType": "int"
										},
										"sink": {
											"name": "IDSuchSchablone",
											"type": "Int32",
											"physicalType": "int"
										}
									},
									{
										"source": {
											"name": "IDJobkette",
											"type": "Int32",
											"physicalType": "int"
										},
										"sink": {
											"name": "IDJobkette",
											"type": "Int32",
											"physicalType": "int"
										}
									},
									{
										"source": {
											"name": "IsRelaissprachenAktiv",
											"type": "Int32",
											"physicalType": "int"
										},
										"sink": {
											"name": "IsRelaissprachenAktiv",
											"type": "Int32",
											"physicalType": "int"
										}
									},
									{
										"source": {
											"name": "Exportiert",
											"type": "Int32",
											"physicalType": "int"
										},
										"sink": {
											"name": "Exportiert",
											"type": "Int32",
											"physicalType": "int"
										}
									},
									{
										"source": {
											"name": "RechnungsempfaengerKundeID",
											"type": "Int32",
											"physicalType": "int"
										},
										"sink": {
											"name": "RechnungsempfaengerKundeID",
											"type": "Int32",
											"physicalType": "int"
										}
									},
									{
										"source": {
											"name": "RechnungsempfaengerAnsprechpartnerID",
											"type": "Int32",
											"physicalType": "int"
										},
										"sink": {
											"name": "RechnungsempfaengerAnsprechpartnerID",
											"type": "Int32",
											"physicalType": "int"
										}
									},
									{
										"source": {
											"name": "DolmetschAdressVorlageID",
											"type": "Int32",
											"physicalType": "int"
										},
										"sink": {
											"name": "DolmetschAdressVorlageID",
											"type": "Int32",
											"physicalType": "int"
										}
									},
									{
										"source": {
											"name": "WithMemoAlertRechnungAnlage",
											"type": "Int32",
											"physicalType": "int"
										},
										"sink": {
											"name": "WithMemoAlertRechnungAnlage",
											"type": "Int32",
											"physicalType": "int"
										}
									},
									{
										"source": {
											"name": "IDPositionSchablone",
											"type": "Int32",
											"physicalType": "int"
										},
										"sink": {
											"name": "IDPositionSchablone",
											"type": "Int32",
											"physicalType": "int"
										}
									},
									{
										"source": {
											"name": "MwSt_Satz1_Rundung",
											"type": "Int32",
											"physicalType": "int"
										},
										"sink": {
											"name": "MwSt_Satz1_Rundung",
											"type": "Int32",
											"physicalType": "int"
										}
									},
									{
										"source": {
											"name": "MwSt_Satz2_Rundung",
											"type": "Int32",
											"physicalType": "int"
										},
										"sink": {
											"name": "MwSt_Satz2_Rundung",
											"type": "Int32",
											"physicalType": "int"
										}
									},
									{
										"source": {
											"name": "MwSt_Satz3_Rundung",
											"type": "Int32",
											"physicalType": "int"
										},
										"sink": {
											"name": "MwSt_Satz3_Rundung",
											"type": "Int32",
											"physicalType": "int"
										}
									},
									{
										"source": {
											"name": "MwSt_Satz4_Rundung",
											"type": "Int32",
											"physicalType": "int"
										},
										"sink": {
											"name": "MwSt_Satz4_Rundung",
											"type": "Int32",
											"physicalType": "int"
										}
									},
									{
										"source": {
											"name": "MwSt_Satz5_Rundung",
											"type": "Int32",
											"physicalType": "int"
										},
										"sink": {
											"name": "MwSt_Satz5_Rundung",
											"type": "Int32",
											"physicalType": "int"
										}
									},
									{
										"source": {
											"name": "KostenuebertragungInPosition",
											"type": "Int32",
											"physicalType": "int"
										},
										"sink": {
											"name": "KostenuebertragungInPosition",
											"type": "Int32",
											"physicalType": "int"
										}
									},
									{
										"source": {
											"name": "VertraulichkeitStufeID",
											"type": "Int32",
											"physicalType": "int"
										},
										"sink": {
											"name": "VertraulichkeitStufeID",
											"type": "Int32",
											"physicalType": "int"
										}
									},
									{
										"source": {
											"name": "VertraulichkeitZipPasswort",
											"type": "String",
											"physicalType": "text"
										},
										"sink": {
											"name": "VertraulichkeitZipPasswort",
											"type": "String",
											"physicalType": "varchar"
										}
									},
									{
										"source": {
											"name": "WeitereEmpfaengerFuerProjektEmails",
											"type": "String",
											"physicalType": "text"
										},
										"sink": {
											"name": "WeitereEmpfaengerFuerProjektEmails",
											"type": "String",
											"physicalType": "varchar"
										}
									},
									{
										"source": {
											"name": "ExterneID",
											"type": "String",
											"physicalType": "text"
										},
										"sink": {
											"name": "ExterneID",
											"type": "String",
											"physicalType": "varchar"
										}
									},
									{
										"source": {
											"name": "IsMultiTeamProjekt",
											"type": "Int32",
											"physicalType": "int"
										},
										"sink": {
											"name": "IsMultiTeamProjekt",
											"type": "Int32",
											"physicalType": "int"
										}
									},
									{
										"source": {
											"name": "KundeID_geloescht",
											"type": "Int32",
											"physicalType": "int"
										},
										"sink": {
											"name": "KundeID_geloescht",
											"type": "Int32",
											"physicalType": "int"
										}
									},
									{
										"source": {
											"name": "AnsprechpartnerID_geloescht",
											"type": "Int32",
											"physicalType": "int"
										},
										"sink": {
											"name": "AnsprechpartnerID_geloescht",
											"type": "Int32",
											"physicalType": "int"
										}
									},
									{
										"source": {
											"name": "MWStSatzR",
											"type": "Double",
											"physicalType": "double"
										},
										"sink": {
											"name": "MWStSatzR",
											"type": "Double",
											"physicalType": "float"
										}
									},
									{
										"source": {
											"name": "MWStBruttoR",
											"type": "Double",
											"physicalType": "double"
										},
										"sink": {
											"name": "MWStBruttoR",
											"type": "Double",
											"physicalType": "float"
										}
									},
									{
										"source": {
											"name": "MwSt_SatzR_Rundung",
											"type": "Int32",
											"physicalType": "int"
										},
										"sink": {
											"name": "MwSt_SatzR_Rundung",
											"type": "Int32",
											"physicalType": "int"
										}
									},
									{
										"source": {
											"name": "MWStBasisR",
											"type": "Double",
											"physicalType": "double"
										},
										"sink": {
											"name": "MWStBasisR",
											"type": "Double",
											"physicalType": "float"
										}
									},
									{
										"source": {
											"name": "ErstelltDurchMitarbeiterID",
											"type": "Int32",
											"physicalType": "int"
										},
										"sink": {
											"name": "ErstelltDurchMitarbeiterID",
											"type": "Int32",
											"physicalType": "int"
										}
									}
								],
								"typeConversion": true,
								"typeConversionSettings": {
									"allowDataTruncation": true,
									"treatBooleanAsNumber": false
								}
							}
						}
					},
					{
						"source": {
							"tableName": "auftragassistent"
						},
						"destination": {
							"table": "auftragassistent"
						},
						"copyActivity": {
							"translator": {
								"type": "TabularTranslator",
								"mappings": [
									{
										"source": {
											"name": "AuftragAssistentID",
											"type": "Int32",
											"physicalType": "int"
										},
										"sink": {
											"name": "AuftragAssistentID",
											"type": "Int32",
											"physicalType": "int"
										}
									},
									{
										"source": {
											"name": "IDMitarbeiter",
											"type": "Int32",
											"physicalType": "int"
										},
										"sink": {
											"name": "IDMitarbeiter",
											"type": "Int32",
											"physicalType": "int"
										}
									},
									{
										"source": {
											"name": "PreiseSichtbar",
											"type": "Int32",
											"physicalType": "int"
										},
										"sink": {
											"name": "PreiseSichtbar",
											"type": "Int32",
											"physicalType": "int"
										}
									},
									{
										"source": {
											"name": "Status",
											"type": "Int32",
											"physicalType": "int"
										},
										"sink": {
											"name": "Status",
											"type": "Int32",
											"physicalType": "int"
										}
									},
									{
										"source": {
											"name": "IDMain",
											"type": "Int32",
											"physicalType": "int"
										},
										"sink": {
											"name": "IDMain",
											"type": "Int32",
											"physicalType": "int"
										}
									},
									{
										"source": {
											"name": "ProvisionUmsatz",
											"type": "Double",
											"physicalType": "double"
										},
										"sink": {
											"name": "ProvisionUmsatz",
											"type": "Double",
											"physicalType": "float"
										}
									},
									{
										"source": {
											"name": "ProvisionRohertrag",
											"type": "Double",
											"physicalType": "double"
										},
										"sink": {
											"name": "ProvisionRohertrag",
											"type": "Double",
											"physicalType": "float"
										}
									},
									{
										"source": {
											"name": "ProvisionAssistent",
											"type": "Int32",
											"physicalType": "int"
										},
										"sink": {
											"name": "ProvisionAssistent",
											"type": "Int32",
											"physicalType": "int"
										}
									},
									{
										"source": {
											"name": "ProvisionWaehrungID",
											"type": "Int32",
											"physicalType": "int"
										},
										"sink": {
											"name": "ProvisionWaehrungID",
											"type": "Int32",
											"physicalType": "int"
										}
									},
									{
										"source": {
											"name": "Kurs",
											"type": "Double",
											"physicalType": "double"
										},
										"sink": {
											"name": "Kurs",
											"type": "Double",
											"physicalType": "float"
										}
									},
									{
										"source": {
											"name": "ProjektRolleID",
											"type": "Int32",
											"physicalType": "int"
										},
										"sink": {
											"name": "ProjektRolleID",
											"type": "Int32",
											"physicalType": "int"
										}
									}
								],
								"typeConversion": true,
								"typeConversionSettings": {
									"allowDataTruncation": true,
									"treatBooleanAsNumber": false
								}
							}
						}
					},
					{
						"source": {
							"tableName": "auftrageigenschaft"
						},
						"destination": {
							"table": "auftrageigenschaft"
						},
						"copyActivity": {
							"translator": {
								"type": "TabularTranslator",
								"mappings": [
									{
										"source": {
											"name": "EigenschaftID",
											"type": "Int32",
											"physicalType": "int"
										},
										"sink": {
											"name": "EigenschaftID",
											"type": "Int32",
											"physicalType": "int"
										}
									},
									{
										"source": {
											"name": "IDProjekt",
											"type": "Int32",
											"physicalType": "int"
										},
										"sink": {
											"name": "IDProjekt",
											"type": "Int32",
											"physicalType": "int"
										}
									},
									{
										"source": {
											"name": "IDEigenschaft",
											"type": "Int32",
											"physicalType": "int"
										},
										"sink": {
											"name": "IDEigenschaft",
											"type": "Int32",
											"physicalType": "int"
										}
									},
									{
										"source": {
											"name": "IDWert",
											"type": "Int32",
											"physicalType": "int"
										},
										"sink": {
											"name": "IDWert",
											"type": "Int32",
											"physicalType": "int"
										}
									},
									{
										"source": {
											"name": "Reihenfolge",
											"type": "Int32",
											"physicalType": "int"
										},
										"sink": {
											"name": "Reihenfolge",
											"type": "Int32",
											"physicalType": "int"
										}
									}
								],
								"typeConversion": true,
								"typeConversionSettings": {
									"allowDataTruncation": true,
									"treatBooleanAsNumber": false
								}
							}
						}
					},
					{
						"source": {
							"tableName": "auftragposition"
						},
						"destination": {
							"table": "auftragposition"
						},
						"copyActivity": {
							"translator": {
								"type": "TabularTranslator",
								"mappings": [
									{
										"source": {
											"name": "PositionID",
											"type": "Int32",
											"physicalType": "int"
										},
										"sink": {
											"name": "PositionID",
											"type": "Int32",
											"physicalType": "int"
										}
									},
									{
										"source": {
											"name": "IDMain",
											"type": "Int32",
											"physicalType": "int"
										},
										"sink": {
											"name": "IDMain",
											"type": "Int32",
											"physicalType": "int"
										}
									},
									{
										"source": {
											"name": "PositionsNr",
											"type": "Int32",
											"physicalType": "int"
										},
										"sink": {
											"name": "PositionsNr",
											"type": "Int32",
											"physicalType": "int"
										}
									},
									{
										"source": {
											"name": "Beschreibung",
											"type": "String",
											"physicalType": "longtext"
										},
										"sink": {
											"name": "Beschreibung",
											"type": "String",
											"physicalType": "varchar"
										}
									},
									{
										"source": {
											"name": "Lieferdatum",
											"type": "DateTime",
											"physicalType": "datetime"
										},
										"sink": {
											"name": "Lieferdatum",
											"type": "DateTime",
											"physicalType": "datetime2"
										}
									},
									{
										"source": {
											"name": "Preis",
											"type": "Double",
											"physicalType": "double"
										},
										"sink": {
											"name": "Preis",
											"type": "Decimal",
											"physicalType": "numeric"
										}
									},
									{
										"source": {
											"name": "MWStArt",
											"type": "Int32",
											"physicalType": "int"
										},
										"sink": {
											"name": "MWStArt",
											"type": "Int32",
											"physicalType": "int"
										}
									},
									{
										"source": {
											"name": "Status",
											"type": "Int32",
											"physicalType": "int"
										},
										"sink": {
											"name": "Status",
											"type": "Int32",
											"physicalType": "int"
										}
									},
									{
										"source": {
											"name": "Bemerkung",
											"type": "String",
											"physicalType": "longtext"
										},
										"sink": {
											"name": "Bemerkung",
											"type": "String",
											"physicalType": "varchar"
										}
									},
									{
										"source": {
											"name": "IDRechnung",
											"type": "Int32",
											"physicalType": "int"
										},
										"sink": {
											"name": "IDRechnung",
											"type": "Int32",
											"physicalType": "int"
										}
									},
									{
										"source": {
											"name": "AnlageDatum",
											"type": "DateTime",
											"physicalType": "datetime"
										},
										"sink": {
											"name": "AnlageDatum",
											"type": "DateTime",
											"physicalType": "datetime2"
										}
									},
									{
										"source": {
											"name": "AnsprechpartnerID",
											"type": "Int32",
											"physicalType": "int"
										},
										"sink": {
											"name": "AnsprechpartnerID",
											"type": "Int32",
											"physicalType": "int"
										}
									},
									{
										"source": {
											"name": "QuellspracheID",
											"type": "Int32",
											"physicalType": "int"
										},
										"sink": {
											"name": "QuellspracheID",
											"type": "Int32",
											"physicalType": "int"
										}
									},
									{
										"source": {
											"name": "ZielspracheID",
											"type": "Int32",
											"physicalType": "int"
										},
										"sink": {
											"name": "ZielspracheID",
											"type": "Int32",
											"physicalType": "int"
										}
									},
									{
										"source": {
											"name": "SprachkombinationID",
											"type": "Int32",
											"physicalType": "int"
										},
										"sink": {
											"name": "SprachkombinationID",
											"type": "Int32",
											"physicalType": "int"
										}
									},
									{
										"source": {
											"name": "ReferenceNr",
											"type": "String",
											"physicalType": "text"
										},
										"sink": {
											"name": "ReferenceNr",
											"type": "String",
											"physicalType": "varchar"
										}
									},
									{
										"source": {
											"name": "SollZeit",
											"type": "Int64",
											"physicalType": "bigint"
										},
										"sink": {
											"name": "SollZeit",
											"type": "Int64",
											"physicalType": "bigint"
										}
									},
									{
										"source": {
											"name": "JobketteID",
											"type": "Int32",
											"physicalType": "int"
										},
										"sink": {
											"name": "JobketteID",
											"type": "Int32",
											"physicalType": "int"
										}
									},
									{
										"source": {
											"name": "ForumThreadID",
											"type": "Int32",
											"physicalType": "int"
										},
										"sink": {
											"name": "ForumThreadID",
											"type": "Int32",
											"physicalType": "int"
										}
									},
									{
										"source": {
											"name": "Reihenfolge",
											"type": "Int32",
											"physicalType": "int"
										},
										"sink": {
											"name": "Reihenfolge",
											"type": "Int32",
											"physicalType": "int"
										}
									},
									{
										"source": {
											"name": "ISTLiefertermin",
											"type": "DateTime",
											"physicalType": "datetime"
										},
										"sink": {
											"name": "ISTLiefertermin",
											"type": "DateTime",
											"physicalType": "datetime2"
										}
									},
									{
										"source": {
											"name": "TM_AnalyseDatei",
											"type": "String",
											"physicalType": "text"
										},
										"sink": {
											"name": "TM_AnalyseDatei",
											"type": "String",
											"physicalType": "varchar"
										}
									},
									{
										"source": {
											"name": "StartDatum",
											"type": "DateTime",
											"physicalType": "datetime"
										},
										"sink": {
											"name": "StartDatum",
											"type": "DateTime",
											"physicalType": "datetime2"
										}
									},
									{
										"source": {
											"name": "EndDatum",
											"type": "DateTime",
											"physicalType": "datetime"
										},
										"sink": {
											"name": "EndDatum",
											"type": "DateTime",
											"physicalType": "datetime2"
										}
									},
									{
										"source": {
											"name": "Mengenfaktor",
											"type": "Double",
											"physicalType": "double"
										},
										"sink": {
											"name": "Mengenfaktor",
											"type": "Double",
											"physicalType": "float"
										}
									},
									{
										"source": {
											"name": "MengenfaktorAktiv",
											"type": "Int32",
											"physicalType": "int"
										},
										"sink": {
											"name": "MengenfaktorAktiv",
											"type": "Int32",
											"physicalType": "int"
										}
									},
									{
										"source": {
											"name": "IDAngebotPos",
											"type": "Int32",
											"physicalType": "int"
										},
										"sink": {
											"name": "IDAngebotPos",
											"type": "Int32",
											"physicalType": "int"
										}
									},
									{
										"source": {
											"name": "PreislisteID",
											"type": "Int32",
											"physicalType": "int"
										},
										"sink": {
											"name": "PreislisteID",
											"type": "Int32",
											"physicalType": "int"
										}
									},
									{
										"source": {
											"name": "Automatisch",
											"type": "Int32",
											"physicalType": "int"
										},
										"sink": {
											"name": "Automatisch",
											"type": "Int32",
											"physicalType": "int"
										}
									},
									{
										"source": {
											"name": "StatusDokumente",
											"type": "Int32",
											"physicalType": "int"
										},
										"sink": {
											"name": "StatusDokumente",
											"type": "Int32",
											"physicalType": "int"
										}
									},
									{
										"source": {
											"name": "Kostenstelle",
											"type": "String",
											"physicalType": "varchar"
										},
										"sink": {
											"name": "Kostenstelle",
											"type": "String",
											"physicalType": "varchar"
										}
									},
									{
										"source": {
											"name": "SprachendienstUebertrag",
											"type": "DateTime",
											"physicalType": "datetime"
										},
										"sink": {
											"name": "SprachendienstUebertrag",
											"type": "DateTime",
											"physicalType": "datetime2"
										}
									},
									{
										"source": {
											"name": "ISTLieferbar",
											"type": "DateTime",
											"physicalType": "datetime"
										},
										"sink": {
											"name": "ISTLieferbar",
											"type": "DateTime",
											"physicalType": "datetime2"
										}
									},
									{
										"source": {
											"name": "StandardAPJob",
											"type": "Int32",
											"physicalType": "int"
										},
										"sink": {
											"name": "StandardAPJob",
											"type": "Int32",
											"physicalType": "int"
										}
									},
									{
										"source": {
											"name": "PositionAusJobAustausch",
											"type": "Int32",
											"physicalType": "int"
										},
										"sink": {
											"name": "PositionAusJobAustausch",
											"type": "Int32",
											"physicalType": "int"
										}
									},
									{
										"source": {
											"name": "IDEventmanagerProjekt",
											"type": "Int32",
											"physicalType": "int"
										},
										"sink": {
											"name": "IDEventmanagerProjekt",
											"type": "Int32",
											"physicalType": "int"
										}
									},
									{
										"source": {
											"name": "AnkuendigungStatus",
											"type": "Int32",
											"physicalType": "int"
										},
										"sink": {
											"name": "AnkuendigungStatus",
											"type": "Int32",
											"physicalType": "int"
										}
									},
									{
										"source": {
											"name": "SupervisorMitarbeiterID",
											"type": "Int32",
											"physicalType": "int"
										},
										"sink": {
											"name": "SupervisorMitarbeiterID",
											"type": "Int32",
											"physicalType": "int"
										}
									}
								],
								"typeConversion": true,
								"typeConversionSettings": {
									"allowDataTruncation": true,
									"treatBooleanAsNumber": false
								}
							}
						}
					},
					{
						"source": {
							"tableName": "auftragposzeilenpreis"
						},
						"destination": {
							"table": "auftragposzeilenpreis"
						},
						"copyActivity": {
							"translator": {
								"type": "TabularTranslator",
								"mappings": [
									{
										"source": {
											"name": "PosZeilenpreisID",
											"type": "Int32",
											"physicalType": "int"
										},
										"sink": {
											"name": "PosZeilenpreisID",
											"type": "Int32",
											"physicalType": "int"
										}
									},
									{
										"source": {
											"name": "IDPosition",
											"type": "Int32",
											"physicalType": "int"
										},
										"sink": {
											"name": "IDPosition",
											"type": "Int32",
											"physicalType": "int"
										}
									},
									{
										"source": {
											"name": "Umfang",
											"type": "Double",
											"physicalType": "double"
										},
										"sink": {
											"name": "Umfang",
											"type": "Decimal",
											"physicalType": "numeric"
										}
									},
									{
										"source": {
											"name": "MengeProEinheit",
											"type": "Double",
											"physicalType": "double"
										},
										"sink": {
											"name": "MengeProEinheit",
											"type": "Decimal",
											"physicalType": "numeric"
										}
									},
									{
										"source": {
											"name": "IDPreiseinheit",
											"type": "Int32",
											"physicalType": "int"
										},
										"sink": {
											"name": "IDPreiseinheit",
											"type": "Int32",
											"physicalType": "int"
										}
									},
									{
										"source": {
											"name": "PreisProEinheit",
											"type": "Double",
											"physicalType": "double"
										},
										"sink": {
											"name": "PreisProEinheit",
											"type": "Double",
											"physicalType": "float"
										}
									},
									{
										"source": {
											"name": "MWStArt",
											"type": "Int32",
											"physicalType": "int"
										},
										"sink": {
											"name": "MWStArt",
											"type": "Int32",
											"physicalType": "int"
										}
									},
									{
										"source": {
											"name": "EinkaufsPreisProEinheit",
											"type": "Int32",
											"physicalType": "int"
										},
										"sink": {
											"name": "EinkaufsPreisProEinheit",
											"type": "Int32",
											"physicalType": "int"
										}
									},
									{
										"source": {
											"name": "ZeitProEinheit",
											"type": "Int32",
											"physicalType": "int"
										},
										"sink": {
											"name": "ZeitProEinheit",
											"type": "Int32",
											"physicalType": "int"
										}
									},
									{
										"source": {
											"name": "Gewichtung",
											"type": "Double",
											"physicalType": "double"
										},
										"sink": {
											"name": "Gewichtung",
											"type": "Double",
											"physicalType": "float"
										}
									},
									{
										"source": {
											"name": "MemoZeilenpreis",
											"type": "String",
											"physicalType": "text"
										},
										"sink": {
											"name": "MemoZeilenpreis",
											"type": "String",
											"physicalType": "varchar"
										}
									},
									{
										"source": {
											"name": "Reihenfolge",
											"type": "Int32",
											"physicalType": "int"
										},
										"sink": {
											"name": "Reihenfolge",
											"type": "Int32",
											"physicalType": "int"
										}
									},
									{
										"source": {
											"name": "ZeitProEinheitDouble",
											"type": "Double",
											"physicalType": "double"
										},
										"sink": {
											"name": "ZeitProEinheitDouble",
											"type": "Double",
											"physicalType": "float"
										}
									}
								],
								"typeConversion": true,
								"typeConversionSettings": {
									"allowDataTruncation": true,
									"treatBooleanAsNumber": false
								}
							}
						}
					},
					{
						"source": {
							"tableName": "gutschrift"
						},
						"destination": {
							"table": "gutschrift"
						},
						"copyActivity": {
							"translator": {
								"type": "TabularTranslator",
								"mappings": [
									{
										"source": {
											"name": "GutschriftID",
											"type": "Int32",
											"physicalType": "int"
										},
										"sink": {
											"name": "GutschriftID",
											"type": "Int32",
											"physicalType": "int"
										}
									},
									{
										"source": {
											"name": "RechnungID",
											"type": "Int32",
											"physicalType": "int"
										},
										"sink": {
											"name": "RechnungID",
											"type": "Int32",
											"physicalType": "int"
										}
									},
									{
										"source": {
											"name": "KundeID",
											"type": "Int32",
											"physicalType": "int"
										},
										"sink": {
											"name": "KundeID",
											"type": "Int32",
											"physicalType": "int"
										}
									},
									{
										"source": {
											"name": "Status",
											"type": "Int32",
											"physicalType": "int"
										},
										"sink": {
											"name": "Status",
											"type": "Int32",
											"physicalType": "int"
										}
									},
									{
										"source": {
											"name": "DatumVerrechnet",
											"type": "DateTime",
											"physicalType": "date"
										},
										"sink": {
											"name": "DatumVerrechnet",
											"type": "DateTime",
											"physicalType": "date"
										}
									},
									{
										"source": {
											"name": "Debitorenkonto",
											"type": "String",
											"physicalType": "varchar"
										},
										"sink": {
											"name": "Debitorenkonto",
											"type": "String",
											"physicalType": "varchar"
										}
									},
									{
										"source": {
											"name": "FormularkreisID",
											"type": "Int32",
											"physicalType": "int"
										},
										"sink": {
											"name": "FormularkreisID",
											"type": "Int32",
											"physicalType": "int"
										}
									},
									{
										"source": {
											"name": "WaehrungID",
											"type": "Int32",
											"physicalType": "int"
										},
										"sink": {
											"name": "WaehrungID",
											"type": "Int32",
											"physicalType": "int"
										}
									},
									{
										"source": {
											"name": "Kurs",
											"type": "Double",
											"physicalType": "double"
										},
										"sink": {
											"name": "Kurs",
											"type": "Double",
											"physicalType": "float"
										}
									},
									{
										"source": {
											"name": "AnzeigeGutschriftNummer",
											"type": "String",
											"physicalType": "varchar"
										},
										"sink": {
											"name": "AnzeigeGutschriftNummer",
											"type": "String",
											"physicalType": "varchar"
										}
									},
									{
										"source": {
											"name": "TextModulTextID_1",
											"type": "Int32",
											"physicalType": "int"
										},
										"sink": {
											"name": "TextModulTextID_1",
											"type": "Int32",
											"physicalType": "int"
										}
									},
									{
										"source": {
											"name": "TextModulTextID_2",
											"type": "Int32",
											"physicalType": "int"
										},
										"sink": {
											"name": "TextModulTextID_2",
											"type": "Int32",
											"physicalType": "int"
										}
									},
									{
										"source": {
											"name": "TextModulTextID_3",
											"type": "Int32",
											"physicalType": "int"
										},
										"sink": {
											"name": "TextModulTextID_3",
											"type": "Int32",
											"physicalType": "int"
										}
									},
									{
										"source": {
											"name": "TextModulTextID_4",
											"type": "Int32",
											"physicalType": "int"
										},
										"sink": {
											"name": "TextModulTextID_4",
											"type": "Int32",
											"physicalType": "int"
										}
									},
									{
										"source": {
											"name": "TextModulTextID_5",
											"type": "Int32",
											"physicalType": "int"
										},
										"sink": {
											"name": "TextModulTextID_5",
											"type": "Int32",
											"physicalType": "int"
										}
									},
									{
										"source": {
											"name": "MWStSatz1",
											"type": "Double",
											"physicalType": "double"
										},
										"sink": {
											"name": "MWStSatz1",
											"type": "Double",
											"physicalType": "float"
										}
									},
									{
										"source": {
											"name": "MWStSatz2",
											"type": "Double",
											"physicalType": "double"
										},
										"sink": {
											"name": "MWStSatz2",
											"type": "Double",
											"physicalType": "float"
										}
									},
									{
										"source": {
											"name": "MWStSatz3",
											"type": "Double",
											"physicalType": "double"
										},
										"sink": {
											"name": "MWStSatz3",
											"type": "Double",
											"physicalType": "float"
										}
									},
									{
										"source": {
											"name": "MWStBrutto1",
											"type": "Double",
											"physicalType": "double"
										},
										"sink": {
											"name": "MWStBrutto1",
											"type": "Double",
											"physicalType": "float"
										}
									},
									{
										"source": {
											"name": "MWStBrutto2",
											"type": "Double",
											"physicalType": "double"
										},
										"sink": {
											"name": "MWStBrutto2",
											"type": "Double",
											"physicalType": "float"
										}
									},
									{
										"source": {
											"name": "MWStBrutto3",
											"type": "Double",
											"physicalType": "double"
										},
										"sink": {
											"name": "MWStBrutto3",
											"type": "Double",
											"physicalType": "float"
										}
									},
									{
										"source": {
											"name": "DatumGutschrift",
											"type": "DateTime",
											"physicalType": "date"
										},
										"sink": {
											"name": "DatumGutschrift",
											"type": "DateTime",
											"physicalType": "date"
										}
									},
									{
										"source": {
											"name": "ExportKennzeichen",
											"type": "Int32",
											"physicalType": "int"
										},
										"sink": {
											"name": "ExportKennzeichen",
											"type": "Int32",
											"physicalType": "int"
										}
									},
									{
										"source": {
											"name": "Brutto",
											"type": "Double",
											"physicalType": "double"
										},
										"sink": {
											"name": "Brutto",
											"type": "Double",
											"physicalType": "float"
										}
									},
									{
										"source": {
											"name": "DatumZahlbar",
											"type": "DateTime",
											"physicalType": "date"
										},
										"sink": {
											"name": "DatumZahlbar",
											"type": "DateTime",
											"physicalType": "date"
										}
									},
									{
										"source": {
											"name": "AnsprechpartnerID",
											"type": "Int32",
											"physicalType": "int"
										},
										"sink": {
											"name": "AnsprechpartnerID",
											"type": "Int32",
											"physicalType": "int"
										}
									},
									{
										"source": {
											"name": "AnschriftID",
											"type": "Int32",
											"physicalType": "int"
										},
										"sink": {
											"name": "AnschriftID",
											"type": "Int32",
											"physicalType": "int"
										}
									},
									{
										"source": {
											"name": "ZeichenKunde",
											"type": "String",
											"physicalType": "text"
										},
										"sink": {
											"name": "ZeichenKunde",
											"type": "String",
											"physicalType": "varchar"
										}
									},
									{
										"source": {
											"name": "Gegenstand",
											"type": "String",
											"physicalType": "text"
										},
										"sink": {
											"name": "Gegenstand",
											"type": "String",
											"physicalType": "varchar"
										}
									},
									{
										"source": {
											"name": "KurzBezeichnung",
											"type": "String",
											"physicalType": "text"
										},
										"sink": {
											"name": "KurzBezeichnung",
											"type": "String",
											"physicalType": "varchar"
										}
									},
									{
										"source": {
											"name": "TextModulText_1",
											"type": "String",
											"physicalType": "text"
										},
										"sink": {
											"name": "TextModulText_1",
											"type": "String",
											"physicalType": "varchar"
										}
									},
									{
										"source": {
											"name": "TextModulText_2",
											"type": "String",
											"physicalType": "text"
										},
										"sink": {
											"name": "TextModulText_2",
											"type": "String",
											"physicalType": "varchar"
										}
									},
									{
										"source": {
											"name": "TextModulText_3",
											"type": "String",
											"physicalType": "text"
										},
										"sink": {
											"name": "TextModulText_3",
											"type": "String",
											"physicalType": "varchar"
										}
									},
									{
										"source": {
											"name": "TextModulText_4",
											"type": "String",
											"physicalType": "text"
										},
										"sink": {
											"name": "TextModulText_4",
											"type": "String",
											"physicalType": "varchar"
										}
									},
									{
										"source": {
											"name": "TextModulText_5",
											"type": "String",
											"physicalType": "text"
										},
										"sink": {
											"name": "TextModulText_5",
											"type": "String",
											"physicalType": "varchar"
										}
									},
									{
										"source": {
											"name": "AuftragArtID",
											"type": "Int32",
											"physicalType": "int"
										},
										"sink": {
											"name": "AuftragArtID",
											"type": "Int32",
											"physicalType": "int"
										}
									},
									{
										"source": {
											"name": "MandantID",
											"type": "Int32",
											"physicalType": "int"
										},
										"sink": {
											"name": "MandantID",
											"type": "Int32",
											"physicalType": "int"
										}
									},
									{
										"source": {
											"name": "MWStSatz4",
											"type": "Double",
											"physicalType": "double"
										},
										"sink": {
											"name": "MWStSatz4",
											"type": "Double",
											"physicalType": "float"
										}
									},
									{
										"source": {
											"name": "MWStBrutto4",
											"type": "Double",
											"physicalType": "double"
										},
										"sink": {
											"name": "MWStBrutto4",
											"type": "Double",
											"physicalType": "float"
										}
									},
									{
										"source": {
											"name": "ErloesKontoID",
											"type": "Int32",
											"physicalType": "int"
										},
										"sink": {
											"name": "ErloesKontoID",
											"type": "Int32",
											"physicalType": "int"
										}
									},
									{
										"source": {
											"name": "EndKundeID",
											"type": "Int32",
											"physicalType": "int"
										},
										"sink": {
											"name": "EndKundeID",
											"type": "Int32",
											"physicalType": "int"
										}
									},
									{
										"source": {
											"name": "Anlagedatum",
											"type": "DateTime",
											"physicalType": "datetime"
										},
										"sink": {
											"name": "Anlagedatum",
											"type": "DateTime",
											"physicalType": "datetime2"
										}
									},
									{
										"source": {
											"name": "UserDefined_String1",
											"type": "String",
											"physicalType": "text"
										},
										"sink": {
											"name": "UserDefined_String1",
											"type": "String",
											"physicalType": "varchar"
										}
									},
									{
										"source": {
											"name": "IDBesteuerungsArt",
											"type": "Int32",
											"physicalType": "int"
										},
										"sink": {
											"name": "IDBesteuerungsArt",
											"type": "Int32",
											"physicalType": "int"
										}
									},
									{
										"source": {
											"name": "MWStSatz5",
											"type": "Double",
											"physicalType": "double"
										},
										"sink": {
											"name": "MWStSatz5",
											"type": "Double",
											"physicalType": "float"
										}
									},
									{
										"source": {
											"name": "MWStBrutto5",
											"type": "Double",
											"physicalType": "double"
										},
										"sink": {
											"name": "MWStBrutto5",
											"type": "Double",
											"physicalType": "float"
										}
									},
									{
										"source": {
											"name": "IndirekterKundeID",
											"type": "Int32",
											"physicalType": "int"
										},
										"sink": {
											"name": "IndirekterKundeID",
											"type": "Int32",
											"physicalType": "int"
										}
									},
									{
										"source": {
											"name": "IndirekterKundeAnsprechpartnerID",
											"type": "Int32",
											"physicalType": "int"
										},
										"sink": {
											"name": "IndirekterKundeAnsprechpartnerID",
											"type": "Int32",
											"physicalType": "int"
										}
									},
									{
										"source": {
											"name": "InRohertrag",
											"type": "Int32",
											"physicalType": "int"
										},
										"sink": {
											"name": "InRohertrag",
											"type": "Int32",
											"physicalType": "int"
										}
									},
									{
										"source": {
											"name": "Netto",
											"type": "Double",
											"physicalType": "double"
										},
										"sink": {
											"name": "Netto",
											"type": "Double",
											"physicalType": "float"
										}
									},
									{
										"source": {
											"name": "MwSt_Satz1_Rundung",
											"type": "Int32",
											"physicalType": "int"
										},
										"sink": {
											"name": "MwSt_Satz1_Rundung",
											"type": "Int32",
											"physicalType": "int"
										}
									},
									{
										"source": {
											"name": "MwSt_Satz2_Rundung",
											"type": "Int32",
											"physicalType": "int"
										},
										"sink": {
											"name": "MwSt_Satz2_Rundung",
											"type": "Int32",
											"physicalType": "int"
										}
									},
									{
										"source": {
											"name": "MwSt_Satz3_Rundung",
											"type": "Int32",
											"physicalType": "int"
										},
										"sink": {
											"name": "MwSt_Satz3_Rundung",
											"type": "Int32",
											"physicalType": "int"
										}
									},
									{
										"source": {
											"name": "MwSt_Satz4_Rundung",
											"type": "Int32",
											"physicalType": "int"
										},
										"sink": {
											"name": "MwSt_Satz4_Rundung",
											"type": "Int32",
											"physicalType": "int"
										}
									},
									{
										"source": {
											"name": "MwSt_Satz5_Rundung",
											"type": "Int32",
											"physicalType": "int"
										},
										"sink": {
											"name": "MwSt_Satz5_Rundung",
											"type": "Int32",
											"physicalType": "int"
										}
									},
									{
										"source": {
											"name": "Creator",
											"type": "Int32",
											"physicalType": "int"
										},
										"sink": {
											"name": "Creator",
											"type": "Int32",
											"physicalType": "int"
										}
									},
									{
										"source": {
											"name": "MWStBasis1",
											"type": "Double",
											"physicalType": "double"
										},
										"sink": {
											"name": "MWStBasis1",
											"type": "Double",
											"physicalType": "float"
										}
									},
									{
										"source": {
											"name": "MWStBasis2",
											"type": "Double",
											"physicalType": "double"
										},
										"sink": {
											"name": "MWStBasis2",
											"type": "Double",
											"physicalType": "float"
										}
									},
									{
										"source": {
											"name": "MWStBasis3",
											"type": "Double",
											"physicalType": "double"
										},
										"sink": {
											"name": "MWStBasis3",
											"type": "Double",
											"physicalType": "float"
										}
									},
									{
										"source": {
											"name": "MWStBasis4",
											"type": "Double",
											"physicalType": "double"
										},
										"sink": {
											"name": "MWStBasis4",
											"type": "Double",
											"physicalType": "float"
										}
									},
									{
										"source": {
											"name": "MWStBasis5",
											"type": "Double",
											"physicalType": "double"
										},
										"sink": {
											"name": "MWStBasis5",
											"type": "Double",
											"physicalType": "float"
										}
									},
									{
										"source": {
											"name": "KundeID_geloescht",
											"type": "Int32",
											"physicalType": "int"
										},
										"sink": {
											"name": "KundeID_geloescht",
											"type": "Int32",
											"physicalType": "int"
										}
									},
									{
										"source": {
											"name": "AnsprechpartnerID_geloescht",
											"type": "Int32",
											"physicalType": "int"
										},
										"sink": {
											"name": "AnsprechpartnerID_geloescht",
											"type": "Int32",
											"physicalType": "int"
										}
									},
									{
										"source": {
											"name": "ItalianEInvoice",
											"type": "String",
											"physicalType": "text"
										},
										"sink": {
											"name": "ItalianEInvoice",
											"type": "String",
											"physicalType": "varchar"
										}
									},
									{
										"source": {
											"name": "MWStSatzR",
											"type": "Double",
											"physicalType": "double"
										},
										"sink": {
											"name": "MWStSatzR",
											"type": "Double",
											"physicalType": "float"
										}
									},
									{
										"source": {
											"name": "MWStBruttoR",
											"type": "Double",
											"physicalType": "double"
										},
										"sink": {
											"name": "MWStBruttoR",
											"type": "Double",
											"physicalType": "float"
										}
									},
									{
										"source": {
											"name": "MwSt_SatzR_Rundung",
											"type": "Int32",
											"physicalType": "int"
										},
										"sink": {
											"name": "MwSt_SatzR_Rundung",
											"type": "Int32",
											"physicalType": "int"
										}
									},
									{
										"source": {
											"name": "MWStBasisR",
											"type": "Double",
											"physicalType": "double"
										},
										"sink": {
											"name": "MWStBasisR",
											"type": "Double",
											"physicalType": "float"
										}
									}
								],
								"typeConversion": true,
								"typeConversionSettings": {
									"allowDataTruncation": true,
									"treatBooleanAsNumber": false
								}
							}
						}
					}
				]
			}
		},
		"annotations": []
	}
}