{
	"name": "Copy_sqldb_to_sqldw_mit",
	"properties": {
		"activities": [
			{
				"name": "Copy_8rl",
				"type": "Copy",
				"dependsOn": [],
				"policy": {
					"timeout": "7.00:00:00",
					"retry": 0,
					"retryIntervalInSeconds": 30,
					"secureOutput": false,
					"secureInput": false
				},
				"userProperties": [
					{
						"name": "Source",
						"value": "dbo.mitarbeiter"
					},
					{
						"name": "Destination",
						"value": "dbo.mitarbeiter"
					}
				],
				"typeProperties": {
					"source": {
						"type": "AzureSqlSource",
						"partitionOption": "None"
					},
					"sink": {
						"type": "SqlDWSink",
						"tableOption": "autoCreate"
					},
					"enableStaging": true,
					"stagingSettings": {
						"linkedServiceName": {
							"referenceName": "AzureBlobStorage1",
							"type": "LinkedServiceReference"
						}
					},
					"translator": {
						"type": "TabularTranslator",
						"mappings": [
							{
								"source": {
									"name": "MitarbeiterID",
									"type": "Int32"
								},
								"sink": {
									"name": "MitarbeiterID",
									"type": "Int32"
								}
							},
							{
								"source": {
									"name": "Aktiv",
									"type": "Int32"
								},
								"sink": {
									"name": "Aktiv",
									"type": "Int32"
								}
							},
							{
								"source": {
									"name": "Status",
									"type": "Int32"
								},
								"sink": {
									"name": "Status",
									"type": "Int32"
								}
							},
							{
								"source": {
									"name": "Anrede",
									"type": "Int32"
								},
								"sink": {
									"name": "Anrede",
									"type": "Int32"
								}
							},
							{
								"source": {
									"name": "Vorname",
									"type": "String"
								},
								"sink": {
									"name": "Vorname",
									"type": "String"
								}
							},
							{
								"source": {
									"name": "Titel",
									"type": "String"
								},
								"sink": {
									"name": "Titel",
									"type": "String"
								}
							},
							{
								"source": {
									"name": "Nachname",
									"type": "String"
								},
								"sink": {
									"name": "Nachname",
									"type": "String"
								}
							},
							{
								"source": {
									"name": "Briefanrede",
									"type": "String"
								},
								"sink": {
									"name": "Briefanrede",
									"type": "String"
								}
							},
							{
								"source": {
									"name": "Geburtsdatum",
									"type": "DateTime"
								},
								"sink": {
									"name": "Geburtsdatum",
									"type": "DateTime"
								}
							},
							{
								"source": {
									"name": "BewertungSprachlich",
									"type": "Int32"
								},
								"sink": {
									"name": "BewertungSprachlich",
									"type": "Int32"
								}
							},
							{
								"source": {
									"name": "BewertungFachlich",
									"type": "Int32"
								},
								"sink": {
									"name": "BewertungFachlich",
									"type": "Int32"
								}
							},
							{
								"source": {
									"name": "BewertungTechnisch",
									"type": "Int32"
								},
								"sink": {
									"name": "BewertungTechnisch",
									"type": "Int32"
								}
							},
							{
								"source": {
									"name": "BewertungTerminlich",
									"type": "Int32"
								},
								"sink": {
									"name": "BewertungTerminlich",
									"type": "Int32"
								}
							},
							{
								"source": {
									"name": "BewertungFlexibilitaet",
									"type": "Int32"
								},
								"sink": {
									"name": "BewertungFlexibilitaet",
									"type": "Int32"
								}
							},
							{
								"source": {
									"name": "Memo",
									"type": "String"
								},
								"sink": {
									"name": "Memo",
									"type": "String"
								}
							},
							{
								"source": {
									"name": "Telefon",
									"type": "String"
								},
								"sink": {
									"name": "Telefon",
									"type": "String"
								}
							},
							{
								"source": {
									"name": "Mobil",
									"type": "String"
								},
								"sink": {
									"name": "Mobil",
									"type": "String"
								}
							},
							{
								"source": {
									"name": "Fax",
									"type": "String"
								},
								"sink": {
									"name": "Fax",
									"type": "String"
								}
							},
							{
								"source": {
									"name": "eMail",
									"type": "String"
								},
								"sink": {
									"name": "eMail",
									"type": "String"
								}
							},
							{
								"source": {
									"name": "Bankname",
									"type": "String"
								},
								"sink": {
									"name": "Bankname",
									"type": "String"
								}
							},
							{
								"source": {
									"name": "BLZ",
									"type": "String"
								},
								"sink": {
									"name": "BLZ",
									"type": "String"
								}
							},
							{
								"source": {
									"name": "KontoNr",
									"type": "String"
								},
								"sink": {
									"name": "KontoNr",
									"type": "String"
								}
							},
							{
								"source": {
									"name": "Kontoinhaber",
									"type": "String"
								},
								"sink": {
									"name": "Kontoinhaber",
									"type": "String"
								}
							},
							{
								"source": {
									"name": "Dossier",
									"type": "String"
								},
								"sink": {
									"name": "Dossier",
									"type": "String"
								}
							},
							{
								"source": {
									"name": "NichtVerfuegbarVon",
									"type": "DateTime"
								},
								"sink": {
									"name": "NichtVerfuegbarVon",
									"type": "DateTime"
								}
							},
							{
								"source": {
									"name": "NichtVerfuegbarBis",
									"type": "DateTime"
								},
								"sink": {
									"name": "NichtVerfuegbarBis",
									"type": "DateTime"
								}
							},
							{
								"source": {
									"name": "UST_ID",
									"type": "String"
								},
								"sink": {
									"name": "UST_ID",
									"type": "String"
								}
							},
							{
								"source": {
									"name": "AnlageDatum",
									"type": "DateTime"
								},
								"sink": {
									"name": "AnlageDatum",
									"type": "DateTime"
								}
							},
							{
								"source": {
									"name": "ArbeitszeitVon",
									"type": "String"
								},
								"sink": {
									"name": "ArbeitszeitVon",
									"type": "String"
								}
							},
							{
								"source": {
									"name": "ArbeitszeitBis",
									"type": "String"
								},
								"sink": {
									"name": "ArbeitszeitBis",
									"type": "String"
								}
							},
							{
								"source": {
									"name": "Internet",
									"type": "String"
								},
								"sink": {
									"name": "Internet",
									"type": "String"
								}
							},
							{
								"source": {
									"name": "SwiftCode",
									"type": "String"
								},
								"sink": {
									"name": "SwiftCode",
									"type": "String"
								}
							},
							{
								"source": {
									"name": "Bankadresse",
									"type": "String"
								},
								"sink": {
									"name": "Bankadresse",
									"type": "String"
								}
							},
							{
								"source": {
									"name": "IBAN",
									"type": "String"
								},
								"sink": {
									"name": "IBAN",
									"type": "String"
								}
							},
							{
								"source": {
									"name": "SortCode",
									"type": "String"
								},
								"sink": {
									"name": "SortCode",
									"type": "String"
								}
							},
							{
								"source": {
									"name": "FachgebietDossier",
									"type": "String"
								},
								"sink": {
									"name": "FachgebietDossier",
									"type": "String"
								}
							},
							{
								"source": {
									"name": "ReadOnly",
									"type": "Int32"
								},
								"sink": {
									"name": "ReadOnly",
									"type": "Int32"
								}
							},
							{
								"source": {
									"name": "WithMemoAlert",
									"type": "Int32"
								},
								"sink": {
									"name": "WithMemoAlert",
									"type": "Int32"
								}
							},
							{
								"source": {
									"name": "SkypeNr",
									"type": "String"
								},
								"sink": {
									"name": "SkypeNr",
									"type": "String"
								}
							},
							{
								"source": {
									"name": "PreisMemo",
									"type": "String"
								},
								"sink": {
									"name": "PreisMemo",
									"type": "String"
								}
							},
							{
								"source": {
									"name": "ABA",
									"type": "String"
								},
								"sink": {
									"name": "ABA",
									"type": "String"
								}
							},
							{
								"source": {
									"name": "KontoFIBU",
									"type": "String"
								},
								"sink": {
									"name": "KontoFIBU",
									"type": "String"
								}
							},
							{
								"source": {
									"name": "AufwandKonto",
									"type": "String"
								},
								"sink": {
									"name": "AufwandKonto",
									"type": "String"
								}
							},
							{
								"source": {
									"name": "NormStunden",
									"type": "Int32"
								},
								"sink": {
									"name": "NormStunden",
									"type": "Int32"
								}
							},
							{
								"source": {
									"name": "UrlaubsFlag",
									"type": "Int32"
								},
								"sink": {
									"name": "UrlaubsFlag",
									"type": "Int32"
								}
							},
							{
								"source": {
									"name": "VorlageID",
									"type": "Int32"
								},
								"sink": {
									"name": "VorlageID",
									"type": "Int32"
								}
							},
							{
								"source": {
									"name": "ProvisionUmsatz",
									"type": "Double"
								},
								"sink": {
									"name": "ProvisionUmsatz",
									"type": "Double"
								}
							},
							{
								"source": {
									"name": "ProvisionRohertrag",
									"type": "Double"
								},
								"sink": {
									"name": "ProvisionRohertrag",
									"type": "Double"
								}
							},
							{
								"source": {
									"name": "Zeitzone",
									"type": "String"
								},
								"sink": {
									"name": "Zeitzone",
									"type": "String"
								}
							},
							{
								"source": {
									"name": "Arbeitsverhaeltnis",
									"type": "Int32"
								},
								"sink": {
									"name": "Arbeitsverhaeltnis",
									"type": "Int32"
								}
							},
							{
								"source": {
									"name": "MWStArt",
									"type": "Int32"
								},
								"sink": {
									"name": "MWStArt",
									"type": "Int32"
								}
							},
							{
								"source": {
									"name": "TextModulTextID_1",
									"type": "Int32"
								},
								"sink": {
									"name": "TextModulTextID_1",
									"type": "Int32"
								}
							},
							{
								"source": {
									"name": "TextModulTextID_2",
									"type": "Int32"
								},
								"sink": {
									"name": "TextModulTextID_2",
									"type": "Int32"
								}
							},
							{
								"source": {
									"name": "TextModulTextID_3",
									"type": "Int32"
								},
								"sink": {
									"name": "TextModulTextID_3",
									"type": "Int32"
								}
							},
							{
								"source": {
									"name": "TextModulTextID_4",
									"type": "Int32"
								},
								"sink": {
									"name": "TextModulTextID_4",
									"type": "Int32"
								}
							},
							{
								"source": {
									"name": "TextModulTextID_5",
									"type": "Int32"
								},
								"sink": {
									"name": "TextModulTextID_5",
									"type": "Int32"
								}
							},
							{
								"source": {
									"name": "AnschriftID",
									"type": "Int32"
								},
								"sink": {
									"name": "AnschriftID",
									"type": "Int32"
								}
							},
							{
								"source": {
									"name": "Vertragsdatum",
									"type": "DateTime"
								},
								"sink": {
									"name": "Vertragsdatum",
									"type": "DateTime"
								}
							},
							{
								"source": {
									"name": "VertragsdatumEnde",
									"type": "DateTime"
								},
								"sink": {
									"name": "VertragsdatumEnde",
									"type": "DateTime"
								}
							},
							{
								"source": {
									"name": "StandardPreislisteDeaktiviert",
									"type": "Int32"
								},
								"sink": {
									"name": "StandardPreislisteDeaktiviert",
									"type": "Int32"
								}
							},
							{
								"source": {
									"name": "TextModulText_1",
									"type": "String"
								},
								"sink": {
									"name": "TextModulText_1",
									"type": "String"
								}
							},
							{
								"source": {
									"name": "TextModulText_2",
									"type": "String"
								},
								"sink": {
									"name": "TextModulText_2",
									"type": "String"
								}
							},
							{
								"source": {
									"name": "TextModulText_3",
									"type": "String"
								},
								"sink": {
									"name": "TextModulText_3",
									"type": "String"
								}
							},
							{
								"source": {
									"name": "TextModulText_4",
									"type": "String"
								},
								"sink": {
									"name": "TextModulText_4",
									"type": "String"
								}
							},
							{
								"source": {
									"name": "TextModulText_5",
									"type": "String"
								},
								"sink": {
									"name": "TextModulText_5",
									"type": "String"
								}
							},
							{
								"source": {
									"name": "IDBesteuerungsArt",
									"type": "Int32"
								},
								"sink": {
									"name": "IDBesteuerungsArt",
									"type": "Int32"
								}
							},
							{
								"source": {
									"name": "VertragsNummer",
									"type": "String"
								},
								"sink": {
									"name": "VertragsNummer",
									"type": "String"
								}
							},
							{
								"source": {
									"name": "MemoVerwenden",
									"type": "Int32"
								},
								"sink": {
									"name": "MemoVerwenden",
									"type": "Int32"
								}
							},
							{
								"source": {
									"name": "StundenerfassungPreis",
									"type": "Double"
								},
								"sink": {
									"name": "StundenerfassungPreis",
									"type": "Double"
								}
							},
							{
								"source": {
									"name": "Zahlungsfrist",
									"type": "Int32"
								},
								"sink": {
									"name": "Zahlungsfrist",
									"type": "Int32"
								}
							},
							{
								"source": {
									"name": "MandantID",
									"type": "Int32"
								},
								"sink": {
									"name": "MandantID",
									"type": "Int32"
								}
							},
							{
								"source": {
									"name": "PayPal",
									"type": "String"
								},
								"sink": {
									"name": "PayPal",
									"type": "String"
								}
							},
							{
								"source": {
									"name": "BenutzerVorhanden",
									"type": "Int32"
								},
								"sink": {
									"name": "BenutzerVorhanden",
									"type": "Int32"
								}
							},
							{
								"source": {
									"name": "ZahlungsMethode",
									"type": "Int32"
								},
								"sink": {
									"name": "ZahlungsMethode",
									"type": "Int32"
								}
							},
							{
								"source": {
									"name": "AufwandsKontoID",
									"type": "Int32"
								},
								"sink": {
									"name": "AufwandsKontoID",
									"type": "Int32"
								}
							},
							{
								"source": {
									"name": "Austrittsdatum",
									"type": "DateTime"
								},
								"sink": {
									"name": "Austrittsdatum",
									"type": "DateTime"
								}
							},
							{
								"source": {
									"name": "BewertungID",
									"type": "Int32"
								},
								"sink": {
									"name": "BewertungID",
									"type": "Int32"
								}
							},
							{
								"source": {
									"name": "Zahlungsfrist_Regel",
									"type": "Int32"
								},
								"sink": {
									"name": "Zahlungsfrist_Regel",
									"type": "Int32"
								}
							},
							{
								"source": {
									"name": "Moneybookers",
									"type": "String"
								},
								"sink": {
									"name": "Moneybookers",
									"type": "String"
								}
							},
							{
								"source": {
									"name": "Kreditkartennummer",
									"type": "String"
								},
								"sink": {
									"name": "Kreditkartennummer",
									"type": "String"
								}
							},
							{
								"source": {
									"name": "Kreditkartenpruefziffer",
									"type": "String"
								},
								"sink": {
									"name": "Kreditkartenpruefziffer",
									"type": "String"
								}
							},
							{
								"source": {
									"name": "Kreditkartenverfallsdatum",
									"type": "DateTime"
								},
								"sink": {
									"name": "Kreditkartenverfallsdatum",
									"type": "DateTime"
								}
							},
							{
								"source": {
									"name": "LetzterJob",
									"type": "DateTime"
								},
								"sink": {
									"name": "LetzterJob",
									"type": "DateTime"
								}
							},
							{
								"source": {
									"name": "Zusatzkosten",
									"type": "Double"
								},
								"sink": {
									"name": "Zusatzkosten",
									"type": "Double"
								}
							},
							{
								"source": {
									"name": "CurrencyID",
									"type": "Int32"
								},
								"sink": {
									"name": "CurrencyID",
									"type": "Int32"
								}
							},
							{
								"source": {
									"name": "AnsprechpartnerID_Standard",
									"type": "Int32"
								},
								"sink": {
									"name": "AnsprechpartnerID_Standard",
									"type": "Int32"
								}
							},
							{
								"source": {
									"name": "UserDefined_String1",
									"type": "String"
								},
								"sink": {
									"name": "UserDefined_String1",
									"type": "String"
								}
							},
							{
								"source": {
									"name": "UserDefined_String2",
									"type": "String"
								},
								"sink": {
									"name": "UserDefined_String2",
									"type": "String"
								}
							},
							{
								"source": {
									"name": "UserDefined_String3",
									"type": "String"
								},
								"sink": {
									"name": "UserDefined_String3",
									"type": "String"
								}
							},
							{
								"source": {
									"name": "UserDefined_String4",
									"type": "String"
								},
								"sink": {
									"name": "UserDefined_String4",
									"type": "String"
								}
							},
							{
								"source": {
									"name": "Memo_Abwesenheit",
									"type": "String"
								},
								"sink": {
									"name": "Memo_Abwesenheit",
									"type": "String"
								}
							},
							{
								"source": {
									"name": "Vorname_enc",
									"type": "Byte[]"
								},
								"sink": {
									"name": "Vorname_enc",
									"type": "Byte[]"
								}
							},
							{
								"source": {
									"name": "Nachname_enc",
									"type": "Byte[]"
								},
								"sink": {
									"name": "Nachname_enc",
									"type": "Byte[]"
								}
							},
							{
								"source": {
									"name": "Telefon_enc",
									"type": "Byte[]"
								},
								"sink": {
									"name": "Telefon_enc",
									"type": "Byte[]"
								}
							},
							{
								"source": {
									"name": "Geburtsdatum_enc",
									"type": "Byte[]"
								},
								"sink": {
									"name": "Geburtsdatum_enc",
									"type": "Byte[]"
								}
							},
							{
								"source": {
									"name": "ExternalID",
									"type": "String"
								},
								"sink": {
									"name": "ExternalID",
									"type": "String"
								}
							},
							{
								"source": {
									"name": "Kostenstelle",
									"type": "String"
								},
								"sink": {
									"name": "Kostenstelle",
									"type": "String"
								}
							},
							{
								"source": {
									"name": "AngebotPruefungMitarbeiter_1",
									"type": "Int32"
								},
								"sink": {
									"name": "AngebotPruefungMitarbeiter_1",
									"type": "Int32"
								}
							},
							{
								"source": {
									"name": "AngebotPruefungMitarbeiter_2",
									"type": "Int32"
								},
								"sink": {
									"name": "AngebotPruefungMitarbeiter_2",
									"type": "Int32"
								}
							},
							{
								"source": {
									"name": "Budget",
									"type": "Int32"
								},
								"sink": {
									"name": "Budget",
									"type": "Int32"
								}
							},
							{
								"source": {
									"name": "Vorgesetzter1",
									"type": "Int32"
								},
								"sink": {
									"name": "Vorgesetzter1",
									"type": "Int32"
								}
							},
							{
								"source": {
									"name": "Vorgesetzter2",
									"type": "Int32"
								},
								"sink": {
									"name": "Vorgesetzter2",
									"type": "Int32"
								}
							},
							{
								"source": {
									"name": "Website",
									"type": "String"
								},
								"sink": {
									"name": "Website",
									"type": "String"
								}
							},
							{
								"source": {
									"name": "DossierNew",
									"type": "String"
								},
								"sink": {
									"name": "DossierNew",
									"type": "String"
								}
							},
							{
								"source": {
									"name": "FachgebietDossierNew",
									"type": "String"
								},
								"sink": {
									"name": "FachgebietDossierNew",
									"type": "String"
								}
							},
							{
								"source": {
									"name": "AutomaticPaymentEnabled",
									"type": "Int32"
								},
								"sink": {
									"name": "AutomaticPaymentEnabled",
									"type": "Int32"
								}
							},
							{
								"source": {
									"name": "MinimumAutoPayment",
									"type": "Double"
								},
								"sink": {
									"name": "MinimumAutoPayment",
									"type": "Double"
								}
							},
							{
								"source": {
									"name": "FasterPaymentEnabled",
									"type": "Int32"
								},
								"sink": {
									"name": "FasterPaymentEnabled",
									"type": "Int32"
								}
							},
							{
								"source": {
									"name": "ErstellerID",
									"type": "Int32"
								},
								"sink": {
									"name": "ErstellerID",
									"type": "Int32"
								}
							},
							{
								"source": {
									"name": "ProjektRolleID",
									"type": "Int32"
								},
								"sink": {
									"name": "ProjektRolleID",
									"type": "Int32"
								}
							},
							{
								"source": {
									"name": "QuickBooksID",
									"type": "String"
								},
								"sink": {
									"name": "QuickBooksID",
									"type": "String"
								}
							},
							{
								"source": {
									"name": "QBTermsID",
									"type": "Int32"
								},
								"sink": {
									"name": "QBTermsID",
									"type": "Int32"
								}
							},
							{
								"source": {
									"name": "IsAgentur",
									"type": "Int32"
								},
								"sink": {
									"name": "IsAgentur",
									"type": "Int32"
								}
							},
							{
								"source": {
									"name": "RoyaltyTaxEnabled",
									"type": "Int32"
								},
								"sink": {
									"name": "RoyaltyTaxEnabled",
									"type": "Int32"
								}
							},
							{
								"source": {
									"name": "MandantID_Is_Mitarbeiter",
									"type": "Int32"
								},
								"sink": {
									"name": "MandantID_Is_Mitarbeiter",
									"type": "Int32"
								}
							},
							{
								"source": {
									"name": "Kleinauftrag_QuellSpracheID",
									"type": "Int32"
								},
								"sink": {
									"name": "Kleinauftrag_QuellSpracheID",
									"type": "Int32"
								}
							},
							{
								"source": {
									"name": "Kleinauftrag_ZielSpracheID",
									"type": "Int32"
								},
								"sink": {
									"name": "Kleinauftrag_ZielSpracheID",
									"type": "Int32"
								}
							},
							{
								"source": {
									"name": "Abteilung",
									"type": "String"
								},
								"sink": {
									"name": "Abteilung",
									"type": "String"
								}
							},
							{
								"source": {
									"name": "Berufsbezeichnung",
									"type": "String"
								},
								"sink": {
									"name": "Berufsbezeichnung",
									"type": "String"
								}
							},
							{
								"source": {
									"name": "Kreditkartennummer_enc",
									"type": "Byte[]"
								},
								"sink": {
									"name": "Kreditkartennummer_enc",
									"type": "Byte[]"
								}
							},
							{
								"source": {
									"name": "Kreditkartenverfallsdatum_enc",
									"type": "Byte[]"
								},
								"sink": {
									"name": "Kreditkartenverfallsdatum_enc",
									"type": "Byte[]"
								}
							},
							{
								"source": {
									"name": "AngebotPruefung_Siehe_Adminbereich",
									"type": "Int32"
								},
								"sink": {
									"name": "AngebotPruefung_Siehe_Adminbereich",
									"type": "Int32"
								}
							},
							{
								"source": {
									"name": "AngebotPruefungNetto_1",
									"type": "Double"
								},
								"sink": {
									"name": "AngebotPruefungNetto_1",
									"type": "Double"
								}
							},
							{
								"source": {
									"name": "AngebotPruefungNetto_2",
									"type": "Double"
								},
								"sink": {
									"name": "AngebotPruefungNetto_2",
									"type": "Double"
								}
							},
							{
								"source": {
									"name": "FileExchangeType",
									"type": "Int32"
								},
								"sink": {
									"name": "FileExchangeType",
									"type": "Int32"
								}
							},
							{
								"source": {
									"name": "SortingField",
									"type": "String"
								},
								"sink": {
									"name": "SortingField",
									"type": "String"
								}
							},
							{
								"source": {
									"name": "DurchschnittlichesJobFeedback",
									"type": "Double"
								},
								"sink": {
									"name": "DurchschnittlichesJobFeedback",
									"type": "Double"
								}
							},
							{
								"source": {
									"name": "AnzahlJobFeedback",
									"type": "Int32"
								},
								"sink": {
									"name": "AnzahlJobFeedback",
									"type": "Int32"
								}
							},
							{
								"source": {
									"name": "IDAcrossTrustedServer",
									"type": "Int32"
								},
								"sink": {
									"name": "IDAcrossTrustedServer",
									"type": "Int32"
								}
							},
							{
								"source": {
									"name": "AutomatischerBonusAufgrundJobFeedbackAktiv",
									"type": "Int32"
								},
								"sink": {
									"name": "AutomatischerBonusAufgrundJobFeedbackAktiv",
									"type": "Int32"
								}
							},
							{
								"source": {
									"name": "RegistrierungAbgeschlossen",
									"type": "Int32"
								},
								"sink": {
									"name": "RegistrierungAbgeschlossen",
									"type": "Int32"
								}
							},
							{
								"source": {
									"name": "CCEmpfaengerMA_JobanfrageEmails",
									"type": "String"
								},
								"sink": {
									"name": "CCEmpfaengerMA_JobanfrageEmails",
									"type": "String"
								}
							},
							{
								"source": {
									"name": "CCEmpfaengerMA_JobbeauftragungEmails",
									"type": "String"
								},
								"sink": {
									"name": "CCEmpfaengerMA_JobbeauftragungEmails",
									"type": "String"
								}
							},
							{
								"source": {
									"name": "CCEmpfaengerMA_RechnungEmails",
									"type": "String"
								},
								"sink": {
									"name": "CCEmpfaengerMA_RechnungEmails",
									"type": "String"
								}
							},
							{
								"source": {
									"name": "isInaktiveAnsprechpartnerAnzeigen",
									"type": "Int32"
								},
								"sink": {
									"name": "isInaktiveAnsprechpartnerAnzeigen",
									"type": "Int32"
								}
							},
							{
								"source": {
									"name": "Abrechnungsart",
									"type": "Int32"
								},
								"sink": {
									"name": "Abrechnungsart",
									"type": "Int32"
								}
							},
							{
								"source": {
									"name": "AbrechnungsartTagSammelrechnung",
									"type": "Int32"
								},
								"sink": {
									"name": "AbrechnungsartTagSammelrechnung",
									"type": "Int32"
								}
							},
							{
								"source": {
									"name": "FirstJob",
									"type": "DateTime"
								},
								"sink": {
									"name": "FirstJob",
									"type": "DateTime"
								}
							},
							{
								"source": {
									"name": "KontaktHerkunft",
									"type": "String"
								},
								"sink": {
									"name": "KontaktHerkunft",
									"type": "String"
								}
							},
							{
								"source": {
									"name": "isEmail_KontaktanlageEUDSGVO_versandt",
									"type": "Int32"
								},
								"sink": {
									"name": "isEmail_KontaktanlageEUDSGVO_versandt",
									"type": "Int32"
								}
							},
							{
								"source": {
									"name": "Datum_LoeschungBeantragt",
									"type": "DateTime"
								},
								"sink": {
									"name": "Datum_LoeschungBeantragt",
									"type": "DateTime"
								}
							},
							{
								"source": {
									"name": "Datum_LetzteAktion_Anfrage",
									"type": "DateTime"
								},
								"sink": {
									"name": "Datum_LetzteAktion_Anfrage",
									"type": "DateTime"
								}
							},
							{
								"source": {
									"name": "Datum_LetzteAktion_Angebot",
									"type": "DateTime"
								},
								"sink": {
									"name": "Datum_LetzteAktion_Angebot",
									"type": "DateTime"
								}
							},
							{
								"source": {
									"name": "Datum_LetzteAktion_Auftrag",
									"type": "DateTime"
								},
								"sink": {
									"name": "Datum_LetzteAktion_Auftrag",
									"type": "DateTime"
								}
							},
							{
								"source": {
									"name": "Datum_LetzteAktion_Job",
									"type": "DateTime"
								},
								"sink": {
									"name": "Datum_LetzteAktion_Job",
									"type": "DateTime"
								}
							},
							{
								"source": {
									"name": "Datum_LetzteAktion_Rechnung",
									"type": "DateTime"
								},
								"sink": {
									"name": "Datum_LetzteAktion_Rechnung",
									"type": "DateTime"
								}
							},
							{
								"source": {
									"name": "MandantID_Rechnung",
									"type": "Int32"
								},
								"sink": {
									"name": "MandantID_Rechnung",
									"type": "Int32"
								}
							},
							{
								"source": {
									"name": "Bank_Country",
									"type": "Int32"
								},
								"sink": {
									"name": "Bank_Country",
									"type": "Int32"
								}
							},
							{
								"source": {
									"name": "Bank_Currency",
									"type": "Int32"
								},
								"sink": {
									"name": "Bank_Currency",
									"type": "Int32"
								}
							},
							{
								"source": {
									"name": "Skonto",
									"type": "Double"
								},
								"sink": {
									"name": "Skonto",
									"type": "Double"
								}
							},
							{
								"source": {
									"name": "SkontoTage",
									"type": "Int32"
								},
								"sink": {
									"name": "SkontoTage",
									"type": "Int32"
								}
							}
						]
					}
				},
				"inputs": [
					{
						"referenceName": "SourceDataset_8rl",
						"type": "DatasetReference"
					}
				],
				"outputs": [
					{
						"referenceName": "DestinationDataset_8rl",
						"type": "DatasetReference"
					}
				]
			}
		],
		"annotations": []
	}
}